setup.py
throttledsocket/__init__.py
throttledsocket/socketwrapper.py
throttledsocket.egg-info/PKG-INFO
throttledsocket.egg-info/SOURCES.txt
throttledsocket.egg-info/dependency_links.txt
throttledsocket.egg-info/pbr.json
throttledsocket.egg-info/requires.txt
throttledsocket.egg-info/top_level.txt