Metadata-Version: 1.0
Name: throttledsocket
Version: 0.0.2
Summary: Socket wrapper for rate limited network I/O.
Home-page: UNKNOWN
Author: Ashish Dubey
Author-email: ashish.dubey91@gmail.com
License: MIT
Platform: UNKNOWN
